nonebot_plugin_ark_roulette/ArkSrc.py
nonebot_plugin_ark_roulette/__init__.py
nonebot_plugin_ark_roulette/config.py
nonebot_plugin_ark_roulette/handbook.py
nonebot_plugin_ark_roulette/mapping.py
nonebot_plugin_ark_roulette/saveData.py
nonebot_plugin_ark_roulette/schemas.py
nonebot_plugin_ark_roulette/skin.py
nonebot_plugin_ark_roulette/utils.py
nonebot_plugin_ark_roulette-2.0.1.dist-info/LICENSE
nonebot_plugin_ark_roulette-2.0.1.dist-info/METADATA
nonebot_plugin_ark_roulette-2.0.1.dist-info/WHEEL
nonebot_plugin_ark_roulette-2.0.1.dist-info/RECORD
