Metadata-Version: 2.3
Name: nonebot_plugin_ark_roulette
Version: 2.0.1
Summary: 一个用于 NoneBot 的插件，提供明日方舟干员筛选与随机选择功能，适用于群聊娱乐。
License: MIT
Keywords: nonebot,plugin,arknights,roulette,chatbot
Author: 星之游
Requires-Python: >=3.11,<4.0
Classifier: License :: OSI Approved :: MIT License
Classifier: Programming Language :: Python :: 3
Classifier: Programming Language :: Python :: 3.11
Classifier: Programming Language :: Python :: 3.12
Classifier: Programming Language :: Python :: 3.13
Requires-Dist: httpx (>=0.28,<0.29)
Requires-Dist: nonebot-plugin-localstore (>=0.7.4,<0.8.0)
Requires-Dist: nonebot2 (>=2.3.0,<3.0.0)
Project-URL: Homepage, https://github.com/xingzhiyou/nonebot-plugin-ark-roulette
Project-URL: Repository, https://github.com/xingzhiyou/nonebot-plugin-ark-roulette
